openseestools/__init__.py
openseestools/basic.py
openseestools/sectionanalysis.py
openseestools/variableanalysis.py
openseestools/wsection.py
openseestools-0.3.0.dist-info/METADATA
openseestools-0.3.0.dist-info/WHEEL
openseestools-0.3.0.dist-info/top_level.txt
openseestools-0.3.0.dist-info/RECORD
