Metadata-Version: 2.1
Name: openseestools
Version: 0.3.0
Summary: Extensions to OpenSeesPy.
Home-page: https://github.com/otaithleigh/OpenSeesTools
Author: Peter Talley
Author-email: ptalley2@vols.utk.edu
License: UNKNOWN
Platform: UNKNOWN
Classifier: Programming Language :: Python :: 3
Classifier: Operating System :: OS Independent
Classifier: Topic :: Scientific/Engineering
Requires-Python: >=3.7
Requires-Dist: attrs
Requires-Dist: matplotlib
Requires-Dist: numpy
Requires-Dist: pandas (>=1.0)
Requires-Dist: tabulate
